README.rst
setup.cfg
setup.py
src/pytest_browserstack_local/__init__.py
src/pytest_browserstack_local/plugin.py
src/pytest_browserstack_local/process.py
src/pytest_browserstack_local/utils.py
src/pytest_browserstack_local.egg-info/PKG-INFO
src/pytest_browserstack_local.egg-info/SOURCES.txt
src/pytest_browserstack_local.egg-info/dependency_links.txt
src/pytest_browserstack_local.egg-info/entry_points.txt
src/pytest_browserstack_local.egg-info/requires.txt
src/pytest_browserstack_local.egg-info/top_level.txt