Metadata-Version: 1.1
Name: pytest-browserstack-local
Version: 0.5.0
Summary: ``py.test`` plugin to run ``BrowserStackLocal`` in background.
Home-page: https://github.com/kottenator/pytest-browserstack-local
Author: Rostyslav Bryzgunov
Author-email: kottenator@gmail.com
License: MIT
Platform: UNKNOWN
Classifier: Framework :: Pytest
Classifier: Intended Audience :: Developers
Classifier: Topic :: Software Development :: Testing
Classifier: License :: OSI Approved :: MIT License
Classifier: Operating System :: OS Independent
Classifier: Programming Language :: Python :: 3
